xopen/__init__.py
xopen/_version.py
xopen/_version.pyi
xopen/py.typed
xopen-2.0.1.dist-info/LICENSE
xopen-2.0.1.dist-info/METADATA
xopen-2.0.1.dist-info/WHEEL
xopen-2.0.1.dist-info/top_level.txt
xopen-2.0.1.dist-info/RECORD
