Metadata-Version: 2.1
Name: xopen
Version: 2.0.1
Summary: Open compressed files transparently
Author-email: Marcel Martin <marcel.martin@scilifelab.se>, Ruben Vorderman <r.h.p.vorderman@lumc.nl>
License: MIT
Project-URL: homepage, https://github.com/pycompression/xopen/
Classifier: Development Status :: 5 - Production/Stable
Classifier: License :: OSI Approved :: MIT License
Classifier: Programming Language :: Python :: 3
Requires-Python: >=3.8
License-File: LICENSE
Requires-Dist: isal>=1.6.1; platform_machine == "x86_64" or platform_machine == "AMD64" or platform_machine == "aarch64"
Requires-Dist: zlib-ng>=0.4.1; platform_machine == "x86_64" or platform_machine == "AMD64" or platform_machine == "aarch64"
Provides-Extra: dev
Requires-Dist: pytest; extra == "dev"
Provides-Extra: zstd
Requires-Dist: zstandard<1; extra == "zstd"
